{"content": "What a load of tosh #UKIP woman is talking. EU \"expansionism\" is hardly the same as Russia trying to redraw Europe's borders by force #bbcqt", "entities": [{"offset": 84, "type": "ne", "id": 2, "entity": "russia"}, {"offset": 108, "type": "ne", "id": 3, "entity": "europe"}, {"offset": 117, "type": "topic keyword", "id": 4, "entity": "borders"}, {"offset": 44, "type": "topic keyword", "id": 5, "entity": "eu"}, {"offset": 21, "type": "party keyword", "id": 6, "entity": "ukip"}], "topics": [{"topic": "eu and immigration", "id": 1}], "tweet_id": "566012453054853120"}