{"content": "Got rid of bureaucrats \"and we put that money, into 9000 more doctors and nurses\"... to turn the doctors into bureaucrats#BattleForNumber10", "entities": [{"offset": 0, "type": "ne", "id": 2, "entity": "got"}, {"offset": 74, "type": "topic keyword", "id": 3, "entity": "nurses"}, {"offset": 97, "type": "topic keyword", "id": 4, "entity": "doctors"}, {"offset": 62, "type": "topic keyword", "id": 5, "entity": "doctors"}], "topics": [{"topic": "nhs", "id": 1}], "tweet_id": "581209490499960832"}