{"content": "I would have quizzed Ed on his assumption the NHS is safer under Labour and Cameron that the economy is safer with Tories #BattleForNumber10", "entities": [{"offset": 21, "type": "ne", "id": 3, "entity": "ed"}, {"offset": 76, "type": "ne", "id": 4, "entity": "cameron"}, {"entity": "economy", "type": "topic keyword", "id": 5, "offset": 93}, {"offset": 46, "type": "topic keyword", "id": 6, "entity": "nhs"}, {"offset": 115, "type": "party keyword", "id": 7, "entity": "tories"}, {"entity": "labour", "type": "party keyword", "id": 8, "offset": 65}], "topics": [{"topic": "economy", "id": 1}, {"topic": "nhs", "id": 2}], "tweet_id": "581392696159371264"}