{
    "jobId": "reproduction_tdlstm_cc840_mods_momentum_take3_run04",
    "labels": {
        "model": "tdlstm",
        "dataset": "laptops",
        "embedding": "commoncrawl840",
        "miniter": "150",
        "optimizer": "momentum"
    },
    "trainingInput": {
        "scaleTier": "CUSTOM",
        "masterType": "standard",
        "pythonVersion": "3.5",
        "runtimeVersion": "1.12",
        "region": "europe-west1",
        "args": [
            "batch",
            "tdlstm-momentum.txt",
            "--new",
            "--nocolor"
        ]
    }
}