{"content": "#bbcqt - Tory Lords mentality, Lord Freud thought it was ok to give disabked workers \u00a32ph while Lord Fink, thinks tax avoidance is vanilla!", "entities": [{"offset": 96, "type": "ne", "id": 2, "entity": "lord fink"}, {"offset": 31, "type": "ne", "id": 3, "entity": "lord freud"}, {"entity": "tax avoidance", "type": "topic keyword", "id": 4, "offset": 114}, {"entity": "tory", "type": "party keyword", "id": 5, "offset": 9}], "topics": [{"topic": "public spending", "id": 1}], "tweet_id": "566017427243548672"}