{"content": "@bbcquestiontime If you are going to let millions of immigrants settle here (1/2M in last 5 years !!) then we need HOUSES and JOBS #BBCQT", "entities": [{"offset": 0, "type": "ne", "id": 2, "entity": "@bbcquestiontime"}, {"offset": 115, "type": "ne", "id": 3, "entity": "houses"}, {"offset": 132, "type": "ne", "id": 4, "entity": "bbcqt"}, {"offset": 126, "type": "ne", "id": 5, "entity": "jobs"}, {"offset": 53, "type": "topic keyword", "id": 6, "entity": "immigrants"}], "topics": [{"topic": "eu and immigration", "id": 1}], "tweet_id": "578699540359942144"}