{"content": "How can we respect mp's who accept a 15% pay rise when teachers/nurses/police and fire service have all had an effective payCUT? #Ge2015", "entities": [{"offset": 121, "type": "ne", "id": 5, "entity": "paycut"}, {"offset": 71, "type": "topic keyword", "id": 6, "entity": "police"}, {"entity": "teachers", "type": "topic keyword", "id": 7, "offset": 55}, {"offset": 64, "type": "topic keyword", "id": 8, "entity": "nurses"}, {"entity": "pay rise", "type": "topic keyword", "id": 9, "offset": 41}], "topics": [{"topic": "nhs", "id": 1}, {"topic": "education", "id": 2}, {"topic": "crime", "id": 3}, {"topic": "public spending", "id": 4}], "tweet_id": "581209052111331328"}